{"episode_list":[{"episode_id":"1","episode_name":"\u4e2d\u91ce\u6709\u9999Vi\uff9a\uff6f\uff7d\uff9d\uff74\uff8b\uff9f\uff7f\uff70\uff84\uff9e1","episode_voice":"1"},{"episode_id":"2","episode_name":"\u4e2d\u91ce\u6709\u9999Vo\uff9a\uff6f\uff7d\uff9d\uff74\uff8b\uff9f\uff7f\uff70\uff84\uff9e1","episode_voice":"1"},{"episode_id":"3","episode_name":"\u4e2d\u91ce\u6709\u9999Da\uff9a\uff6f\uff7d\uff9d\uff74\uff8b\uff9f\uff7f\uff70\uff84\uff9e1","episode_voice":"1"},{"episode_id":"4","episode_name":"\u4e2d\u91ce\u6709\u9999\uff7d\uff83\uff6f\uff8c\uff9f\uff71\uff6f\uff8c\uff9f\uff74\uff8b\uff9f\uff7f\uff70\uff84\uff9e1","episode_voice":"1"},{"episode_id":"5","episode_name":"\u4e2d\u91ce\u6709\u9999Vi\uff9a\uff6f\uff7d\uff9d\uff74\uff8b\uff9f\uff7f\uff70\uff84\uff9e2","episode_voice":"1"},{"episode_id":"6","episode_name":"\u4e2d\u91ce\u6709\u9999Vo\uff9a\uff6f\uff7d\uff9d\uff74\uff8b\uff9f\uff7f\uff70\uff84\uff9e2","episode_voice":"1"},{"episode_id":"7","episode_name":"\u4e2d\u91ce\u6709\u9999Da\uff9a\uff6f\uff7d\uff9d\uff74\uff8b\uff9f\uff7f\uff70\uff84\uff9e2","episode_voice":"1"},{"episode_id":"8","episode_name":"\u4e2d\u91ce\u6709\u9999\uff7d\uff83\uff6f\uff8c\uff9f\uff71\uff6f\uff8c\uff9f\uff74\uff8b\uff9f\uff7f\uff70\uff84\uff9e2","episode_voice":"1"}],"idol_message":"\uff8c\uff9f\uff9b\uff83\uff9e\uff6d\uff70\uff7b\uff70\u306e\u8863\u88c5\u9078\u3073\u3092\u5b66\u3073\u307e\u3059\uff61\u3042\u3068\uff64\u3042\u305f\u3057\u2026\u304b\uff64\u304b\u308f\u3044\u3044\u8863\u88c5\u3060\u3068\u2026\u3046\u308c\u3057\u3044\u3067\u3059\u2026!","idol_attribute":"1"}